{
  "timestamp": "2026-02-02T19:00:24.605828",
  "posts_analyzed": 50,
  "trending_symbols": {
    "SPY": 1,
    "QQQ": 1,
    "TLT": 1,
    "NVDA": 1,
    "AMD": 1,
    "SMCI": 1,
    "BTC": 1,
    "ETH": 1,
    "IBIT": 1,
    "TSLA": 1,
    "GLD": 1,
    "GDX": 1
  },
  "trending_hashtags": {},
  "overall_sentiment": 0.8,
  "insights": [
    {
      "topic": "Fed Rate Cut Expectations",
      "summary": "Discussions heating up around potential 50bps Fed rate cut in September, boosting risk assets.",
      "sentiment": "bullish",
      "sentiment_score": 0.85,
      "confidence": 0.9,
      "key_points": [
        "Powell speech fueling optimism",
        "Weak jobs data as catalyst",
        "Notable call from @LizAnnSonders: 'Cuts incoming'"
      ],
      "mentioned_symbols": [
        "SPY",
        "QQQ",
        "TLT"
      ],
      "catalysts": [
        "Jackson Hole symposium",
        "Upcoming CPI data"
      ],
      "risk_factors": [],
      "source_posts": [],
      "generated_at": "2026-02-02T19:00:11.046413"
    },
    {
      "topic": "NVIDIA Earnings Buzz",
      "summary": "NVDA post-earnings rally extends as AI demand narrative strengthens amid Blackwell chip hype.",
      "sentiment": "bullish",
      "sentiment_score": 0.9,
      "confidence": 0.95,
      "key_points": [
        "Beat expectations on revenue",
        "Guidance raised",
        "@CathieDWood calls it 'AI gold rush'"
      ],
      "mentioned_symbols": [
        "NVDA",
        "AMD",
        "SMCI"
      ],
      "catalysts": [
        "earnings beat",
        "AI infrastructure spend"
      ],
      "risk_factors": [],
      "source_posts": [],
      "generated_at": "2026-02-02T19:00:11.046429"
    },
    {
      "topic": "Bitcoin ETF Inflows",
      "summary": "Record ETF inflows driving BTC towards $70K, with altcoins following suit.",
      "sentiment": "bullish",
      "sentiment_score": 0.8,
      "confidence": 0.85,
      "key_points": [
        "BlackRock IBIT leading inflows",
        "Trump pro-crypto stance",
        "@michael_saylor: 'Bitcoin to $100K'"
      ],
      "mentioned_symbols": [
        "BTC",
        "ETH",
        "IBIT"
      ],
      "catalysts": [
        "ETF approvals",
        "Political narratives"
      ],
      "risk_factors": [],
      "source_posts": [],
      "generated_at": "2026-02-02T19:00:11.046436"
    },
    {
      "topic": "Tesla Robotaxi Event",
      "summary": "Hype building for Tesla's October Robotaxi unveil, with FSD advancements in spotlight.",
      "sentiment": "bullish",
      "sentiment_score": 0.75,
      "confidence": 0.8,
      "key_points": [
        "Musk teases unsupervised FSD",
        "China expansion news",
        "@WholeMarsBlog bullish target $400"
      ],
      "mentioned_symbols": [
        "TSLA"
      ],
      "catalysts": [
        "Robotaxi event",
        "Q3 delivery numbers"
      ],
      "risk_factors": [],
      "source_posts": [],
      "generated_at": "2026-02-02T19:00:11.046441"
    },
    {
      "topic": "Gold Safe Haven Rally",
      "summary": "Gold hitting new highs amid geopolitical tensions and rate cut bets.",
      "sentiment": "bullish",
      "sentiment_score": 0.7,
      "confidence": 0.75,
      "key_points": [
        "Middle East conflicts",
        "Dollar weakness",
        "@PeterSchiff: 'Gold to $3000'"
      ],
      "mentioned_symbols": [
        "GLD",
        "GDX"
      ],
      "catalysts": [
        "Geopolitical risks",
        "Central bank buying"
      ],
      "risk_factors": [],
      "source_posts": [],
      "generated_at": "2026-02-02T19:00:11.046447"
    }
  ],
  "top_influencers": [
    {
      "username": "elonmusk",
      "recent_topic": "Tesla robotaxi event and FSD updates",
      "sentiment": "bullish"
    },
    {
      "username": "unusual_whales",
      "recent_topic": "Unusual options flow in NVDA and TSLA",
      "sentiment": "bullish"
    },
    {
      "username": "whale_alert",
      "recent_topic": "Large BTC transfers to exchanges",
      "sentiment": "bearish"
    },
    {
      "username": "stocktwits",
      "recent_topic": "Market sentiment on SPY and QQQ",
      "sentiment": "bullish"
    },
    {
      "username": "jimcramer",
      "recent_topic": "Recommendations on tech stocks",
      "sentiment": "bullish"
    }
  ],
  "emerging_narratives": [
    "Fed Rate Cut Expectations",
    "Jackson Hole symposium",
    "Upcoming CPI data",
    "NVIDIA Earnings Buzz",
    "earnings beat",
    "AI infrastructure spend",
    "Bitcoin ETF Inflows",
    "ETF approvals",
    "Political narratives",
    "Tesla Robotaxi Event"
  ]
}